bifrost_tracing/__init__.py
bifrost_tracing/bifrost_tracing.py
bifrost_tracing/cli.py
bifrost_tracing-0.1.0.dist-info/AUTHORS.rst
bifrost_tracing-0.1.0.dist-info/LICENSE
bifrost_tracing-0.1.0.dist-info/METADATA
bifrost_tracing-0.1.0.dist-info/WHEEL
bifrost_tracing-0.1.0.dist-info/entry_points.txt
bifrost_tracing-0.1.0.dist-info/top_level.txt
bifrost_tracing-0.1.0.dist-info/RECORD
