Metadata-Version: 2.1
Name: bifrost_tracing
Version: 0.1.0
Summary: Bifrost Tracing traces codes used in a notebook
Home-page: https://github.com/jaahn96/bifrost_tracing
Author: Jay Ahn
Author-email: aju960219@gmail.com
License: BSD license
Keywords: bifrost_tracing
Platform: UNKNOWN
Classifier: Development Status :: 2 - Pre-Alpha
Classifier: Intended Audience :: Developers
Classifier: License :: OSI Approved :: BSD License
Classifier: Natural Language :: English
Classifier: Programming Language :: Python :: 3
Classifier: Programming Language :: Python :: 3.6
Classifier: Programming Language :: Python :: 3.7
Classifier: Programming Language :: Python :: 3.8
Requires-Python: >=3.6
License-File: LICENSE
License-File: AUTHORS.rst
